pyqt_style_setter/__init__.py
pyqt_style_setter/styleSetter.py
pyqt_style_setter-0.0.15.dist-info/LICENSE
pyqt_style_setter-0.0.15.dist-info/METADATA
pyqt_style_setter-0.0.15.dist-info/WHEEL
pyqt_style_setter-0.0.15.dist-info/top_level.txt
pyqt_style_setter-0.0.15.dist-info/RECORD
