Metadata-Version: 2.1
Name: pyqt-style-setter
Version: 0.0.15
Summary: PyQt style setter
Home-page: https://github.com/yjg30737/pyqt-style-setter.git
Author: Jung Gyu Yoon
Author-email: yjg30737@gmail.com
License: MIT
Platform: UNKNOWN
License-File: LICENSE
Requires-Dist: PyQt5 (>=5.8)
Requires-Dist: pyqt-dark-gray-theme (>=0.0.1)
Requires-Dist: pyqt-light-gray-theme (>=0.0.1)
Requires-Dist: pyqt-svg-button (>=0.0.1)
